Metadata-Version: 2.1
Name: wbfbd
Version: 0.0.0
Summary: wbfbd
Home-page: https://github.com/Functional-Bus-Description-Language/PyWbFBD
Author: Michał Kruszewski
Author-email: mkru@protonmail.com
License: GPLv3+
Keywords: Bus Interface,Control and Status Registers,Co-simulation,Documentation Generation,Electronic Design Automation,Electronic Systems,Firmware Generation,FPGA,Hardware Design,HDL,Hierarchical Register Description,Memory,Register Addressing,Register Synthesis,RTL,Software Generation,SystemVerilog,VHDL
Platform: UNKNOWN
Classifier: Topic :: Scientific/Engineering :: Electronic Design Automation (EDA)
Classifier: Topic :: Software Development :: Testing
Classifier: Topic :: Software Development :: Quality Assurance
Classifier: Topic :: Utilities
Classifier: Intended Audience :: End Users/Desktop
Classifier: License :: OSI Approved :: GNU General Public License v3 or later (GPLv3+)
